oedialect/__init__.py
oedialect/compiler.py
oedialect/dbapi.py
oedialect/dialect.py
oedialect/engine.py
oedialect/error.py
oedialect/requirements.py
oedialect/settings.py
oedialect-0.1.1.dist-info/LICENSE
oedialect-0.1.1.dist-info/METADATA
oedialect-0.1.1.dist-info/WHEEL
oedialect-0.1.1.dist-info/entry_points.txt
oedialect-0.1.1.dist-info/top_level.txt
oedialect-0.1.1.dist-info/RECORD
