Metadata-Version: 2.1
Name: oedialect
Version: 0.1.1
Summary: SQL-Alchemy dialect for the OpenEnergy Platform
Home-page: https://github.com/openego/oedialect
Author: MGlauer
Author-email: martinglauer89@gmail.com
Keywords: postgres,open,energy,database,sql,rest
License-File: LICENSE
Requires-Dist: sqlalchemy >=1.3.16
Requires-Dist: requests >=2.13
Requires-Dist: psycopg2-binary
Requires-Dist: geoalchemy2 <0.7.0
Requires-Dist: shapely
Requires-Dist: python-dateutil
Provides-Extra: tests
Requires-Dist: black ; extra == 'tests'
Requires-Dist: tox ; extra == 'tests'
Requires-Dist: pytest ==5.3 ; extra == 'tests'
Requires-Dist: pandas ; extra == 'tests'
Requires-Dist: sqlahelper ; extra == 'tests'
Requires-Dist: geojson ; extra == 'tests'
